pippity/__init__.py
pippity/module.py
pippity-1.2.1.dist-info/LICENSE
pippity-1.2.1.dist-info/METADATA
pippity-1.2.1.dist-info/WHEEL
pippity-1.2.1.dist-info/top_level.txt
pippity-1.2.1.dist-info/RECORD
