Metadata-Version: 2.2
Name: pippity
Version: 1.2.1
Summary: Install your PyPi packages without access to pip. Install packages, straight from inside your script.
Author-email: uukelele-scratch <robustrobot11@gmail.com>
License: MIT License
Project-URL: Homepage, https://github.com/uukelele-scratch/pippity
Project-URL: Repository, https://github.com/uukelele-scratch/pippity
Classifier: Programming Language :: Python :: 3
Classifier: License :: OSI Approved :: MIT License
Classifier: Operating System :: OS Independent
Requires-Python: >=3.7
License-File: LICENSE
